censuscoding/VERSION
censuscoding/__init__.py
censuscoding/__main__.py
censuscoding/data/blkgrp-zip-street-names.csv
censuscoding/data/blkgrp-zip-street-nums.csv
test/__init__.py
test/test_blockgroup_assignment.py
censuscoding-0.1.0.dist-info/LICENSE
censuscoding-0.1.0.dist-info/METADATA
censuscoding-0.1.0.dist-info/WHEEL
censuscoding-0.1.0.dist-info/entry_points.txt
censuscoding-0.1.0.dist-info/top_level.txt
censuscoding-0.1.0.dist-info/RECORD
