Metadata-Version: 2.1
Name: censuscoding
Version: 0.1.0
Summary: Censuscoding: determine the Census blockgroup for a street address
Home-page: https://github.com/ripl-org/censuscoding
Author: Mark Howison
Author-email: mhowison@ripl.org
License: UNKNOWN
Platform: UNKNOWN
Classifier: Development Status :: 3 - Alpha
Classifier: License :: Free for non-commercial use
Classifier: Intended Audience :: Science/Research
Classifier: Natural Language :: English
Classifier: Operating System :: POSIX :: Linux
Classifier: Programming Language :: Python :: 3.7
Classifier: Topic :: Scientific/Engineering
Provides: censuscoding
Requires-Python: >=3.7,<3.10
License-File: LICENSE
Requires-Dist: pandas
Requires-Dist: usaddress
